{"_default": {"4": {"name": "Eat Soap", "category": "Weekly", "last_completed_by": null, "complete": true}, "6": {"name": "Hug Kids", "category": "Monthly", "last_completed_by": null, "complete": false}, "7": {"name": "Do thing", "category": "Weekly", "last_completed_by": null, "complete": false}, "8": {"name": "Do Thing", "category": "Daily", "last_completed_by": null, "complete": true}, "9": {"name": "Do Thiiing", "category": "Monthly", "last_completed_by": null, "complete": false}, "11": {"name": "asdfa", "category": "Monthly", "last_completed_by": null, "complete": false}, "12": {"name": "dothing", "category": "Weekly", "last_completed_by": null, "complete": false}, "13": {"name": "Do another thing", "category": "Daily", "last_completed_by": null, "complete": true}, "14": {"name": "23", "category": "Weekly", "last_completed_by": null, "complete": true}, "15": {"name": "asdf", "category": "Daily", "last_completed_by": null, "complete": false}, "16": {"name": "sdfasdf", "category": "Weekly", "last_completed_by": null, "complete": false}, "17": {"name": "24", "category": "Weekly", "last_completed_by": null, "complete": false}, "18": {"name": "weekly", "category": "Weekly", "last_completed_by": null, "complete": false}}}